colab_easy_ui/ColabEasyUI.py
colab_easy_ui/ColabInternalFetcher.py
colab_easy_ui/EasyFileUploaderInternal.py
colab_easy_ui/Functions.py
colab_easy_ui/__init__.py
colab_easy_ui/const.py
colab_easy_ui/data/Response.py
colab_easy_ui/frontend/dist/assets/buymeacoffee.png
colab_easy_ui/frontend/dist/assets/icons/blank.png
colab_easy_ui/frontend/dist/assets/icons/file-text.svg
colab_easy_ui/frontend/dist/assets/icons/flect.png
colab_easy_ui/frontend/dist/assets/icons/folder.svg
colab_easy_ui/frontend/dist/assets/icons/github.svg
colab_easy_ui/frontend/dist/assets/icons/help-circle.svg
colab_easy_ui/frontend/dist/assets/icons/home.svg
colab_easy_ui/frontend/dist/assets/icons/linkedin.svg
colab_easy_ui/frontend/dist/assets/icons/noimage.png
colab_easy_ui/frontend/dist/assets/icons/tool.svg
colab_easy_ui/frontend/dist/assets/icons/twitter.svg
colab_easy_ui/frontend/dist/favicon.ico
colab_easy_ui/frontend/dist/index.html
colab_easy_ui/frontend/dist/index.js
colab_easy_ui/frontend_fileuploader/dist/assets/buymeacoffee.png
colab_easy_ui/frontend_fileuploader/dist/assets/icons/blank.png
colab_easy_ui/frontend_fileuploader/dist/assets/icons/file-text.svg
colab_easy_ui/frontend_fileuploader/dist/assets/icons/flect.png
colab_easy_ui/frontend_fileuploader/dist/assets/icons/folder.svg
colab_easy_ui/frontend_fileuploader/dist/assets/icons/github.svg
colab_easy_ui/frontend_fileuploader/dist/assets/icons/help-circle.svg
colab_easy_ui/frontend_fileuploader/dist/assets/icons/home.svg
colab_easy_ui/frontend_fileuploader/dist/assets/icons/linkedin.svg
colab_easy_ui/frontend_fileuploader/dist/assets/icons/noimage.png
colab_easy_ui/frontend_fileuploader/dist/assets/icons/tool.svg
colab_easy_ui/frontend_fileuploader/dist/assets/icons/twitter.svg
colab_easy_ui/frontend_fileuploader/dist/favicon.ico
colab_easy_ui/frontend_fileuploader/dist/index.html
colab_easy_ui/frontend_fileuploader/dist/index.js
colab_easy_ui/frontend_fileuploader/dist/index.js.LICENSE.txt
colab_easy_ui/main.py
colab_easy_ui-0.1.115.dist-info/METADATA
colab_easy_ui-0.1.115.dist-info/WHEEL
colab_easy_ui-0.1.115.dist-info/entry_points.txt
colab_easy_ui-0.1.115.dist-info/RECORD
