Metadata-Version: 2.1
Name: colab-easy-ui
Version: 0.1.115
Summary: 
Author: w-okada
Requires-Python: >=3.10,<4.0
Classifier: Programming Language :: Python :: 3
Classifier: Programming Language :: Python :: 3.10
Classifier: Programming Language :: Python :: 3.11
Classifier: Programming Language :: Python :: 3.12
Requires-Dist: fastapi (>=0.108.0,<0.109.0)
Requires-Dist: fire (>=0.5.0,<0.6.0)
Requires-Dist: nest-asyncio (>=1.5.8,<2.0.0)
Requires-Dist: python-multipart (>=0.0.6,<0.0.7)
Requires-Dist: uvicorn (>=0.25.0,<0.26.0)
